odoo/addons/account_invoice_sale_origin_link/README.rst
odoo/addons/account_invoice_sale_origin_link/__init__.py
odoo/addons/account_invoice_sale_origin_link/__manifest__.py
odoo/addons/account_invoice_sale_origin_link/i18n/account_invoice_sale_origin_link.pot
odoo/addons/account_invoice_sale_origin_link/i18n/fr_FR.po
odoo/addons/account_invoice_sale_origin_link/models/__init__.py
odoo/addons/account_invoice_sale_origin_link/models/account_move.py
odoo/addons/account_invoice_sale_origin_link/readme/CONTRIBUTORS.rst
odoo/addons/account_invoice_sale_origin_link/readme/DESCRIPTION.rst
odoo/addons/account_invoice_sale_origin_link/static/description/icon.png
odoo/addons/account_invoice_sale_origin_link/static/description/index.html
odoo/addons/account_invoice_sale_origin_link/tests/__init__.py
odoo/addons/account_invoice_sale_origin_link/tests/test_account_invoice_sale_origin_link.py
odoo13_addon_account_invoice_sale_origin_link-13.0.1.0.1.dev5.dist-info/METADATA
odoo13_addon_account_invoice_sale_origin_link-13.0.1.0.1.dev5.dist-info/WHEEL
odoo13_addon_account_invoice_sale_origin_link-13.0.1.0.1.dev5.dist-info/top_level.txt
odoo13_addon_account_invoice_sale_origin_link-13.0.1.0.1.dev5.dist-info/RECORD
